{
  "symbol": "HAH",
  "processed_by": "VCI",
  "data_source": "VCI",
  "created_at": "2025-08-14T09:12:36.379252",
  "company_name": "Công ty TNHH Vận tải và Xếp dỡ Hải An được thành lập năm 2009. Công ty hoạt động chính trên lĩnh khai thác cảng và vận tải. Công ty hiện đang sở hữu đội tàu với sức chứa gần 16.000 TEUs. Địa bàn kinh doanh của công ty bao gồm các tỉnh, thành phố lớn như Hà Nội, Hải Phòng, Thành phố Hồ Chí Minh, Đà Nẵng, Bà Rịa- Vũng Tàu. Cảng Hải An được đánh giá là có lợi thế cạnh tranh do vị trí của cảng nằm ở hạ lưu sông Cấm, mớn nước sâu hơn, nên đường vào cảng rất rộng, mực nước sâu nên có lợi thế trong việc đón các tàu có trọng tải lớn lên tới 20.000DWT. Năm 2015, công ty chính thức được niêm yết tại Sở Giao dịch Chứng khoán Thành phố Hồ Chí Minh",
  "exchange": "HOSE",
  "industry": "Vận tải",
  "company_profile": "<div style=\"FONT-FAMILY: Arial; FONT-SIZE: 10pt;\">\r\n<p>C&ocirc;ng ty cổ phần Vận tải v&agrave; Xếp dỡ Hải An (HAH)&nbsp;tiền th&acirc;n l&agrave; C&ocirc;ng ty TNHH Vận tải v&agrave; Xếp dỡ Hải An được th&agrave;nh lập năm 2009. C&ocirc;ng ty hoạt động ch&iacute;nh tr&ecirc;n lĩnh khai th&aacute;c cảng v&agrave; vận tải. C&ocirc;ng ty hiện đang sở hữu đội t&agrave;u với sức chứa gần 16.000 TEUs.&nbsp;Địa b&agrave;n kinh doanh của c&ocirc;ng ty bao gồm c&aacute;c tỉnh, th&agrave;nh phố lớn như H&agrave; Nội, Hải Ph&ograve;ng, Th&agrave;nh phố Hồ Ch&iacute; Minh, Đ&agrave; Nẵng, B&agrave; Rịa- Vũng T&agrave;u.&nbsp;Cảng Hải An được đ&aacute;nh gi&aacute; l&agrave; c&oacute; lợi thế cạnh tranh do vị tr&iacute; của cảng nằm ở hạ lưu s&ocirc;ng Cấm, mớn nước s&acirc;u hơn, n&ecirc;n đường v&agrave;o cảng rất rộng, mực nước s&acirc;u n&ecirc;n c&oacute; lợi thế trong việc đ&oacute;n c&aacute;c t&agrave;u c&oacute; trọng tải lớn l&ecirc;n tới 20.000DWT. Năm 2015, c&ocirc;ng ty ch&iacute;nh thức được ni&ecirc;m yết tại Sở Giao dịch Chứng kho&aacute;n Th&agrave;nh phố Hồ Ch&iacute; Minh (HOSE).</p>\r\n</div>\r\n",
  "established_year": null,
  "employees": null,
  "website": null,
  "current_price": 63200,
  "market_cap": 8209327217600,
  "outstanding_shares": 129894418,
  "revenue": 1274665190278,
  "net_income": 361617919453,
  "total_assets": 2293111635429,
  "shareholders_equity": 1.6899744485519341,
  "pe_ratio": 9.571657587,
  "pb_ratio": 2.6508201842,
  "roe": 0.3065258304,
  "roa": 0.1437099614,
  "debt_to_equity": 0.6899744486,
  "current_ratio": 1.5808640202,
  "gross_margin": 0.4444469906575575,
  "net_margin": 0.28369639510915995
}