{
  "symbol": "HCD",
  "processed_by": "VCI",
  "data_source": "VCI",
  "created_at": "2025-08-15T07:07:31.097300",
  "company_name": "Công ty Cổ phần Đầu tư Sản xuất và Thương mại HCD",
  "exchange": "HOSE",
  "industry": "Hóa chất",
  "company_profile": "<div style=\"FONT-FAMILY: Arial; FONT-SIZE: 10pt;\">C&ocirc;ng ty Cổ phần Đầu tư Sản xuất v&agrave; Thương mại HCD (HCD), tiền th&acirc;n l&agrave; C&ocirc;ng ty Cổ phần Luyện kim HCD, được th&agrave;nh lập ng&agrave;y 06/12/2011. Hoạt động kinh doanh ch&iacute;nh của C&ocirc;ng ty l&agrave; xuất nhập khẩu, cung ứng v&agrave; ph&acirc;n phối hạt nhựa nguy&ecirc;n sinh, v&agrave; kinh doanh th&eacute;p x&acirc;y dựng, th&eacute;p h&igrave;nh. B&ecirc;n cạnh đ&oacute;, để mở rộng lĩnh vực kinh doanh v&agrave; tận dụng lợi thế cạnh tranh, C&ocirc;ng ty đang đầu tư x&acirc;y dựng nh&agrave; m&aacute;y sản xuất bao b&igrave; nhựa tự hủy với tổng c&ocirc;ng suất đạt 7.200 &ndash; 8.000 tấn/năm dự kiến sẽ đi v&agrave;o hoạt động v&agrave;o năm 2017. Trong lĩnh vực kinh doanh hạt nhựa, C&ocirc;ng ty l&agrave; đối t&aacute;c của nhiều Tập đo&agrave;n cung cấp hạt nhựa nổi tiếng từ c&aacute;c nước tr&ecirc;n thế giới như H&agrave;n Quốc, Nhật Bản, v&agrave; Th&aacute;i Lan.B&ecirc;n cạnh đ&oacute;, C&ocirc;ng ty cũng l&agrave; đại l&yacute; ph&acirc;n phối th&eacute;p cấp I của nhiều doanh nghiệp sản xuất th&eacute;p lớn trong nước như Th&eacute;p H&ograve;a Ph&aacute;p, POMINA v&agrave; c&aacute;c nh&agrave; nhập khẩu th&eacute;p kh&aacute;c.&nbsp;Ng&agrave;y 04/07/2016, HCD ch&iacute;nh thức giao dịch tr&ecirc;n Sở Giao dịch Chứng kho&aacute;n Th&agrave;nh phố Hồ Ch&iacute; Minh (HOSE).</div>\r\n",
  "established_year": null,
  "employees": null,
  "website": null,
  "current_price": 7880,
  "market_cap": 291235470080,
  "outstanding_shares": 36958816,
  "revenue": 186221563913,
  "net_income": 5878440212,
  "total_assets": 627911293633,
  "shareholders_equity": 1.6634670300241996,
  "pe_ratio": 10.7632143622,
  "pb_ratio": 0.5874461576,
  "roe": 0.055661096,
  "roa": 0.0325192392,
  "debt_to_equity": 0.66346703,
  "current_ratio": 1.9089860218,
  "gross_margin": 0.061132057146284564,
  "net_margin": 0.031566914639092614
}