{
  "symbol": "TCH",
  "processed_by": "VCI",
  "data_source": "VCI",
  "created_at": "2025-08-14T08:11:15.682788",
  "company_name": null,
  "exchange": "HOSE",
  "industry": "Bất động sản",
  "company_profile": "<div style=\"FONT-FAMILY: Arial; FONT-SIZE: 10pt;\">C&ocirc;ng ty Cổ phần Đầu tư Dịch vụ T&agrave;i ch&iacute;nh Ho&agrave;ng Huy (TCH) c&oacute; tiền th&acirc;n l&agrave; C&ocirc;ng ty TNHH Thương mại Ho&agrave;ng Huy, được th&agrave;nh lập v&agrave;o th&aacute;ng 10/1995. TCH chuy&ecirc;n hoạt động trong lĩnh vực đầu tư kinh doanh bất động sản v&agrave;&nbsp;lắp r&aacute;p ph&acirc;n phối xe &ocirc; t&ocirc; đầu k&eacute;o.&nbsp;TCH hiện đang l&agrave;&nbsp;nh&agrave;&nbsp;ph&acirc;n phối ch&iacute;nh h&atilde;ng xe tải thương hiệu International của h&atilde;ng Navistar (Hoa Kỳ) v&agrave;&nbsp;c&aacute;c d&ograve;ng xe&nbsp;Dongfeng (Trung Quốc) tại thị trường Việt Nam. C&ocirc;ng ty đ&atilde; x&acirc;y dựng hệ thống ph&acirc;n phối xe tải với&nbsp;hơn 25 đại l&yacute; tr&ecirc;n to&agrave;n quốc.&nbsp;Trong lĩnh vực đầu tư kinh doanh bất động sản, TCH đ&atilde; triển khai&nbsp;thực hiện&nbsp;nhiều dự &aacute;n quy m&ocirc;&nbsp;lớn&nbsp;như&nbsp;Hoang Huy Commerce, Hoang Huy New&nbsp;City, Hoang Huy Green River, ....&nbsp;TCH được giao dịch tr&ecirc;n Sở Giao dịch Chứng kho&aacute;n Th&agrave;nh phố Hồ Ch&iacute; Minh (HOSE) từ năm 2016.</div>\r\n",
  "established_year": null,
  "employees": null,
  "website": null,
  "current_price": 26000,
  "market_cap": 17373611918000,
  "outstanding_shares": 668215843,
  "revenue": 390355429992,
  "net_income": 37872945883,
  "total_assets": 12332761716771,
  "shareholders_equity": 1.1947505639308218,
  "pe_ratio": 23.1075266558,
  "pb_ratio": 1.879989576,
  "roe": 0.0795469909,
  "roa": 0.0496892975,
  "debt_to_equity": 0.1947505639,
  "current_ratio": 8.1309415574,
  "gross_margin": 0.2890966193228381,
  "net_margin": 0.0970216960572988
}