{
  "symbol": "VOS",
  "processed_by": "VCI",
  "data_source": "VCI",
  "created_at": "2025-08-15T07:17:35.343636",
  "company_name": "Công ty Cổ phần Vận tải Biển Việt Nam",
  "exchange": "HOSE",
  "industry": "Vận tải",
  "company_profile": "<div style=\"FONT-FAMILY: Arial; FONT-SIZE: 10pt;\">\r\n<p>C&ocirc;ng ty Cổ phần Vận tải Biển Việt Nam (VOS) tiền th&acirc;n l&agrave; C&ocirc;ng ty Vận tải biển Việt Nam được th&agrave;nh lập năm 1970. Hoạt động kinh doanh ch&iacute;nh của C&ocirc;ng ty bao gồm vận tải đường biển v&agrave; c&aacute;c dịch vụ h&agrave;ng hải kh&aacute;c như: đại k&yacute; t&agrave;u biển, đại l&yacute; vận tải đa phương thức, huấn luyện - đ&agrave;o tạo, cung ứng xuất khẩu thuyền vi&ecirc;n. C&ocirc;ng ty&nbsp;sở hữu đội t&agrave;u 11&nbsp;chiếc với tổng tải trọng 358.101 DWT. Vận tải h&agrave;ng kh&ocirc; l&agrave; sở trường v&agrave; thế mạnh của C&ocirc;ng ty. Mặt h&agrave;ng chuy&ecirc;n chở của C&ocirc;ng ty bao&nbsp;gồm gạo, than, n&ocirc;ng sản, xi măng, clinker, ph&acirc;n b&oacute;n, vật tư sắt th&eacute;p xuất khẩu của Việt Nam v&agrave; thế giới, đặc biệt l&agrave; c&aacute;c nước Đ&ocirc;ng Nam &Aacute;, Trung Đ&ocirc;ng v&agrave; Ch&acirc;u Phi. VOS ch&iacute;nh thức được ni&ecirc;m yết v&agrave; giao dịch tại Sở Giao dịch Chứng kho&aacute;n Th&agrave;nh phố Hồ Ch&iacute; Minh từ năm 2010.</p>\r\n</div>\r\n",
  "established_year": null,
  "employees": null,
  "website": null,
  "current_price": 16250,
  "market_cap": 2275000000000,
  "outstanding_shares": 140000000,
  "revenue": 836393570707,
  "net_income": 10284949227,
  "total_assets": 1918790228892,
  "shareholders_equity": 1.964865987176043,
  "pe_ratio": -34.1026542926,
  "pb_ratio": 1.2871778258,
  "roe": -0.0347027009,
  "roa": -0.0214551806,
  "debt_to_equity": 0.9648659872,
  "current_ratio": 2.4586486917,
  "gross_margin": 0.039587815599720806,
  "net_margin": 0.012305180881301732
}